{
  "updated": "2026-07-12T23:01:15",
  "daily_date": "20260711",
  "weekly_date": "20260712",
  "daily": [
    {
      "rnum": "1",
      "rank": "1",
      "rankInten": "0",
      "rankOldAndNew": "OLD",
      "movieCd": "20259946",
      "movieNm": "모아나",
      "openDt": "2026-07-08",
      "salesAmt": "2016093460",
      "salesShare": "37.5",
      "salesInten": "1338598480",
      "salesChange": "197.6",
      "salesAcc": "3809582690",
      "audiCnt": "180128",
      "audiInten": "121340",
      "audiChange": "206.4",
      "audiAcc": "346172",
      "scrnCnt": "1449",
      "showCnt": "6004",
      "poster_url": "https://search.pstatic.net/common?type=o&size=304x456&quality=100&direct=true&src=https%3A%2F%2Fs.pstatic.net%2Fmovie.phinf%2F20260709_287%2F1783562694126cqy6R_JPEG%2Fmovie_image.jpg%3Ftype%3Dw640_2",
      "synopsis": "끝없는 바다 너머 새로운 세상을 꿈꾸던 모투누이 섬의 소녀 모아나. 어느 날 모투누이에 깊은 어둠이 드리우자, 모아나는 저주에 빠진 섬을 구하기 위해 전설의 ...",
      "naver_rating": "9.67",
      "directors": [
        "토마스 케일"
      ],
      "actors": [
        "드웨인 존슨",
        "캐서린 라가이아"
      ],
      "genres": [
        "어드벤처",
        "액션"
      ],
      "nations": [
        "미국"
      ],
      "rating": "전체관람가",
      "runtime": "115",
      "movieNmEn": "Moana"
    },
    {
      "rnum": "2",
      "rank": "2",
      "rankInten": "0",
      "rankOldAndNew": "OLD",
      "movieCd": "20242402",
      "movieNm": "눈동자",
      "openDt": "2026-06-24",
      "salesAmt": "1215593510",
      "salesShare": "22.6",
      "salesInten": "659077450",
      "salesChange": "118.4",
      "salesAcc": "12070384380",
      "audiCnt": "111500",
      "audiInten": "60770",
      "audiChange": "119.8",
      "audiAcc": "1181677",
      "scrnCnt": "1026",
      "showCnt": "3833",
      "poster_url": "https://search.pstatic.net/common?type=o&size=304x456&quality=100&direct=true&src=https%3A%2F%2Fs.pstatic.net%2Fmovie.phinf%2F20260626_123%2F1782458347543sx2kJ_JPEG%2Fmovie_image.jpg%3Ftype%3Dw640_2",
      "synopsis": "유전병으로 점차 시력을 잃어가는 사진작가 ‘서진’(신민아). 어느 날, 자신보다 먼저 시력을 잃었지만 도예가로 성공한 쌍둥이 동생 ‘서인’(신민아)이 죽어있는 ...",
      "naver_rating": "8.02",
      "directors": [
        "염지호"
      ],
      "actors": [
        "신민아",
        "김남희",
        "이승룡",
        "김영아",
        "박경진"
      ],
      "genres": [
        "스릴러"
      ],
      "nations": [
        "한국"
      ],
      "rating": "15세이상관람가",
      "runtime": "105",
      "movieNmEn": "THE  EYES"
    },
    {
      "rnum": "3",
      "rank": "3",
      "rankInten": "0",
      "rankOldAndNew": "OLD",
      "movieCd": "20259781",
      "movieNm": "토이 스토리 5",
      "openDt": "2026-06-17",
      "salesAmt": "1126656460",
      "salesShare": "20.9",
      "salesInten": "744447930",
      "salesChange": "194.8",
      "salesAcc": "25485280950",
      "audiCnt": "103554",
      "audiInten": "67249",
      "audiChange": "185.2",
      "audiAcc": "2481662",
      "scrnCnt": "994",
      "showCnt": "3128",
      "poster_url": "https://search.pstatic.net/common?type=o&size=304x456&quality=100&direct=true&src=https%3A%2F%2Fs.pstatic.net%2Fmovie.phinf%2F20260617_109%2F1781663561154vA0bW_JPEG%2Fmovie_image.jpg%3Ftype%3Dw640_2",
      "synopsis": "“시대는 변해도, 친구들은 영원하다\" 스마트 태블릿 ’릴리패드'의 등장으로 온라인 세계에 모여들게 된 아이들. 친구들과 어울리기 위해 ‘보니’에게도 ‘릴리패드’...",
      "naver_rating": "9.37",
      "directors": [
        "앤드류 스탠튼"
      ],
      "actors": [
        "톰 행크스",
        "팀 알렌",
        "조앤 쿠삭",
        "그레타 리"
      ],
      "genres": [
        "애니메이션",
        "어드벤처",
        "코미디"
      ],
      "nations": [
        "미국"
      ],
      "rating": "전체관람가",
      "runtime": "101",
      "movieNmEn": "Toy Story 5"
    },
    {
      "rnum": "4",
      "rank": "4",
      "rankInten": "0",
      "rankOldAndNew": "OLD",
      "movieCd": "20262902",
      "movieNm": "다윗",
      "openDt": "2026-07-10",
      "salesAmt": "235651590",
      "salesShare": "4.4",
      "salesInten": "153646370",
      "salesChange": "187.4",
      "salesAcc": "471051210",
      "audiCnt": "23132",
      "audiInten": "15291",
      "audiChange": "195",
      "audiAcc": "48767",
      "scrnCnt": "649",
      "showCnt": "1343",
      "poster_url": "https://search.pstatic.net/common?type=o&size=304x456&quality=100&direct=true&src=https%3A%2F%2Fs.pstatic.net%2Fmovie.phinf%2F20260710_234%2F1783665438821VAl3y_JPEG%2Fmovie_image.jpg%3Ftype%3Dw640_2",
      "synopsis": "평범한 목동 다윗, 두려움을 넘어 역사가 되다! 소년 다윗은 어느 날 선지자 사무엘로부터 왕이 될 운명을 듣게 되지만, 그것이 무엇을 의미하는지 알기도 전에 ...",
      "naver_rating": "9.67",
      "directors": [
        "필 커닝햄",
        "브렌트 도스"
      ],
      "actors": [
        "브랜든 엥그먼",
        "필 위크함",
        "브라이언 스티베일",
        "아담 골드",
        "미리 메시카"
      ],
      "genres": [
        "애니메이션"
      ],
      "nations": [
        "남아프리카공화국",
        "미국"
      ],
      "rating": "전체관람가",
      "runtime": "109",
      "movieNmEn": "David"
    },
    {
      "rnum": "5",
      "rank": "5",
      "rankInten": "0",
      "rankOldAndNew": "OLD",
      "movieCd": "20252402",
      "movieNm": "군체",
      "openDt": "2026-05-21",
      "salesAmt": "175498700",
      "salesShare": "3.3",
      "salesInten": "87705100",
      "salesChange": "99.9",
      "salesAcc": "62117619430",
      "audiCnt": "15644",
      "audiInten": "7807",
      "audiChange": "99.6",
      "audiAcc": "5900794",
      "scrnCnt": "517",
      "showCnt": "777",
      "poster_url": "https://search.pstatic.net/common?type=o&size=304x456&quality=100&direct=true&src=https%3A%2F%2Fs.pstatic.net%2Fmovie.phinf%2F20260521_199%2F1779327167613y2t7q_JPEG%2Fmovie_image.jpg%3Ftype%3Dw640_2",
      "synopsis": "서울 도심의 초고층 빌딩에서 정체불명의 집단 감염사태가 발생한다. 건물은 순식간에 봉쇄되고, 그 안에 있던 사람들은 그대로 고립된다. 처음에는 짐승처럼 기...",
      "naver_rating": "7.88",
      "directors": [
        "연상호"
      ],
      "actors": [
        "전지현",
        "구교환",
        "지창욱",
        "신현빈",
        "김신록"
      ],
      "genres": [
        "액션",
        "스릴러"
      ],
      "nations": [
        "한국"
      ],
      "rating": "15세이상관람가",
      "runtime": "122",
      "movieNmEn": "COLONY"
    },
    {
      "rnum": "6",
      "rank": "6",
      "rankInten": "1",
      "rankOldAndNew": "OLD",
      "movieCd": "20263530",
      "movieNm": "마티 슈프림",
      "openDt": "2026-07-01",
      "salesAmt": "71051950",
      "salesShare": "1.3",
      "salesInten": "31381850",
      "salesChange": "79.1",
      "salesAcc": "1031588460",
      "audiCnt": "5870",
      "audiInten": "2344",
      "audiChange": "66.5",
      "audiAcc": "97201",
      "scrnCnt": "195",
      "showCnt": "214",
      "poster_url": "https://search.pstatic.net/common?type=o&size=304x456&quality=100&direct=true&src=https%3A%2F%2Fs.pstatic.net%2Fmovie.phinf%2F20260610_239%2F1781068492766CU2dN_JPEG%2Fmovie_image.jpg%3Ftype%3Dw640_2",
      "synopsis": "\"어떤 대가를 치르더라도 반드시 가장 높은 곳으로!\" 탁구로 인생 역전을 꿈꾸는 마티 마우저는 굴욕적인 패배 후 누구도 무시할 수 없는 성공을 손에 넣기로 결심한다. 최고가 ...",
      "naver_rating": "8.16",
      "directors": [
        "조쉬 사프디"
      ],
      "actors": [
        "티모시 샬라메",
        "기네스 팰트로우",
        "오데사 아지온",
        "타일러 더 크리에이터",
        "아벨 페라라"
      ],
      "genres": [
        "드라마"
      ],
      "nations": [
        "미국"
      ],
      "rating": "15세이상관람가",
      "runtime": "149",
      "movieNmEn": "Marty Supreme"
    },
    {
      "rnum": "7",
      "rank": "7",
      "rankInten": "5",
      "rankOldAndNew": "OLD",
      "movieCd": "20264027",
      "movieNm": "극장판 도라에몽: 신 진구의 해저비밀성",
      "openDt": "2026-07-01",
      "salesAmt": "58551550",
      "salesShare": "1.1",
      "salesInten": "45328050",
      "salesChange": "342.8",
      "salesAcc": "490319400",
      "audiCnt": "5580",
      "audiInten": "4376",
      "audiChange": "363.5",
      "audiAcc": "52270",
      "scrnCnt": "199",
      "showCnt": "347",
      "poster_url": "https://search.pstatic.net/common?type=o&size=304x456&quality=100&direct=true&src=https%3A%2F%2Fs.pstatic.net%2Fmovie.phinf%2F20260701_60%2F1782880689685LGkLk_JPEG%2Fmovie_image.jpg%3Ftype%3Dw640_2",
      "synopsis": "이번 여름방학은 바닷속 캠핑이다! 숨이 멎을 듯한 놀라움이 가득한 두근두근 해저 대모험! 여름방학 캠핑 장소를 두고 의견이 갈린 진구와 친구들은 도라에몽의 제안으로 바...",
      "naver_rating": "8.79",
      "directors": [
        "야지마 테츠오"
      ],
      "actors": [
        "윤아영",
        "김정아",
        "조현정",
        "이현주",
        "최낙윤"
      ],
      "genres": [
        "애니메이션"
      ],
      "nations": [
        "일본"
      ],
      "rating": "전체관람가",
      "runtime": "101",
      "movieNmEn": "Doraemon the Movie: New Nobita and the Castle of the Undersea Devil"
    },
    {
      "rnum": "8",
      "rank": "8",
      "rankInten": "0",
      "rankOldAndNew": "NEW",
      "movieCd": "20233219",
      "movieNm": "호프",
      "openDt": "2026-07-15",
      "salesAmt": "76470000",
      "salesShare": "1.4",
      "salesInten": "76470000",
      "salesChange": "100",
      "salesAcc": "84456000",
      "audiCnt": "5098",
      "audiInten": "5098",
      "audiChange": "100",
      "audiAcc": "5632",
      "scrnCnt": "27",
      "showCnt": "27",
      "poster_url": "",
      "synopsis": "지원해 줄 인력들은 산불을 끄러 갔고, 이젠 통신도 두절됐다. 호포 출장소의 ‘범석’과 ‘성애’는 노인들뿐인 마을을 지키기 위해 사투를 벌이고, 놈을 쫓아 산으로 ...",
      "naver_rating": "",
      "directors": [
        "나홍진"
      ],
      "actors": [
        "황정민",
        "조인성",
        "정호연",
        "테일러 러셀",
        "카메론 브리튼"
      ],
      "genres": [
        "SF",
        "스릴러",
        "액션"
      ],
      "nations": [
        "한국"
      ],
      "rating": "15세이상관람가",
      "runtime": "156",
      "movieNmEn": "HOPE"
    },
    {
      "rnum": "9",
      "rank": "9",
      "rankInten": "-3",
      "rankOldAndNew": "OLD",
      "movieCd": "20248252",
      "movieNm": "와일드 씽",
      "openDt": "2026-06-03",
      "salesAmt": "42988250",
      "salesShare": "0.8",
      "salesInten": "9978700",
      "salesChange": "30.2",
      "salesAcc": "12841514190",
      "audiCnt": "4813",
      "audiInten": "1026",
      "audiChange": "27.1",
      "audiAcc": "1329512",
      "scrnCnt": "301",
      "showCnt": "379",
      "poster_url": "https://search.pstatic.net/common?type=o&size=304x456&quality=100&direct=true&src=https%3A%2F%2Fs.pstatic.net%2Fmovie.phinf%2F20260612_104%2F1781234312440vFV51_JPEG%2Fmovie_image.jpg%3Ftype%3Dw640_2",
      "synopsis": "",
      "naver_rating": "",
      "directors": [
        "손재곤"
      ],
      "actors": [
        "강동원",
        "엄태구",
        "박지현",
        "오정세",
        "안현호"
      ],
      "genres": [
        "코미디"
      ],
      "nations": [
        "한국"
      ],
      "rating": "12세이상관람가",
      "runtime": "107",
      "movieNmEn": "Wild Sing"
    },
    {
      "rnum": "10",
      "rank": "10",
      "rankInten": "0",
      "rankOldAndNew": "OLD",
      "movieCd": "20263030",
      "movieNm": "백룸",
      "openDt": "2026-05-27",
      "salesAmt": "42134300",
      "salesShare": "0.8",
      "salesInten": "20073400",
      "salesChange": "91",
      "salesAcc": "12877548160",
      "audiCnt": "3479",
      "audiInten": "1672",
      "audiChange": "92.5",
      "audiAcc": "1206168",
      "scrnCnt": "119",
      "showCnt": "154",
      "poster_url": "",
      "synopsis": "\"시작은 호기심이었다\" 그곳은 대체 무엇인가? 낯설지만 익숙한 세계 출구도 입구도 찾을 수 없다. 당신도 입장하시겠습니까?",
      "naver_rating": "7.95",
      "directors": [
        "케인 파슨스"
      ],
      "actors": [
        "치웨텔 에지오포",
        "레나테 레인스베"
      ],
      "genres": [
        "공포(호러)",
        "스릴러"
      ],
      "nations": [
        "미국"
      ],
      "rating": "15세이상관람가",
      "runtime": "110",
      "movieNmEn": "Backrooms"
    }
  ],
  "weekly": [
    {
      "rnum": "1",
      "rank": "1",
      "rankInten": "0",
      "rankOldAndNew": "NEW",
      "movieCd": "20259946",
      "movieNm": "모아나",
      "openDt": "2026-07-08",
      "salesAmt": "5633626720",
      "salesShare": "31.1",
      "salesInten": "5633626720",
      "salesChange": "100.0",
      "salesAcc": "5633626720",
      "audiCnt": "511078",
      "audiInten": "511078",
      "audiChange": "100.0",
      "audiAcc": "511078",
      "scrnCnt": "1449",
      "showCnt": "27024",
      "poster_url": "https://search.pstatic.net/common?type=o&size=304x456&quality=100&direct=true&src=https%3A%2F%2Fs.pstatic.net%2Fmovie.phinf%2F20260709_287%2F1783562694126cqy6R_JPEG%2Fmovie_image.jpg%3Ftype%3Dw640_2",
      "synopsis": "끝없는 바다 너머 새로운 세상을 꿈꾸던 모투누이 섬의 소녀 모아나. 어느 날 모투누이에 깊은 어둠이 드리우자, 모아나는 저주에 빠진 섬을 구하기 위해 전설의 ...",
      "naver_rating": "9.67",
      "directors": [
        "토마스 케일"
      ],
      "actors": [
        "드웨인 존슨",
        "캐서린 라가이아"
      ],
      "genres": [
        "어드벤처",
        "액션"
      ],
      "nations": [
        "미국"
      ],
      "rating": "전체관람가",
      "runtime": "115",
      "movieNmEn": "Moana"
    },
    {
      "rnum": "2",
      "rank": "2",
      "rankInten": "0",
      "rankOldAndNew": "OLD",
      "movieCd": "20242402",
      "movieNm": "눈동자",
      "openDt": "2026-06-24",
      "salesAmt": "4565468300",
      "salesShare": "25.2",
      "salesInten": "-899861430",
      "salesChange": "-16.5",
      "salesAcc": "13109484530",
      "audiCnt": "434573",
      "audiInten": "-102895",
      "audiChange": "-19.1",
      "audiAcc": "1277263",
      "scrnCnt": "1035",
      "showCnt": "25042",
      "poster_url": "https://search.pstatic.net/common?type=o&size=304x456&quality=100&direct=true&src=https%3A%2F%2Fs.pstatic.net%2Fmovie.phinf%2F20260626_123%2F1782458347543sx2kJ_JPEG%2Fmovie_image.jpg%3Ftype%3Dw640_2",
      "synopsis": "유전병으로 점차 시력을 잃어가는 사진작가 ‘서진’(신민아). 어느 날, 자신보다 먼저 시력을 잃었지만 도예가로 성공한 쌍둥이 동생 ‘서인’(신민아)이 죽어있는 ...",
      "naver_rating": "8.02",
      "directors": [
        "염지호"
      ],
      "actors": [
        "신민아",
        "김남희",
        "이승룡",
        "김영아",
        "박경진"
      ],
      "genres": [
        "스릴러"
      ],
      "nations": [
        "한국"
      ],
      "rating": "15세이상관람가",
      "runtime": "105",
      "movieNmEn": "THE  EYES"
    },
    {
      "rnum": "3",
      "rank": "3",
      "rankInten": "-2",
      "rankOldAndNew": "OLD",
      "movieCd": "20259781",
      "movieNm": "토이 스토리 5",
      "openDt": "2026-06-17",
      "salesAmt": "3785179210",
      "salesShare": "20.9",
      "salesInten": "-2288689660",
      "salesChange": "-37.7",
      "salesAcc": "26545659950",
      "audiCnt": "361839",
      "audiInten": "-239326",
      "audiChange": "-39.8",
      "audiAcc": "2580327",
      "scrnCnt": "1026",
      "showCnt": "19749",
      "poster_url": "https://search.pstatic.net/common?type=o&size=304x456&quality=100&direct=true&src=https%3A%2F%2Fs.pstatic.net%2Fmovie.phinf%2F20260617_109%2F1781663561154vA0bW_JPEG%2Fmovie_image.jpg%3Ftype%3Dw640_2",
      "synopsis": "“시대는 변해도, 친구들은 영원하다\" 스마트 태블릿 ’릴리패드'의 등장으로 온라인 세계에 모여들게 된 아이들. 친구들과 어울리기 위해 ‘보니’에게도 ‘릴리패드’...",
      "naver_rating": "9.37",
      "directors": [
        "앤드류 스탠튼"
      ],
      "actors": [
        "톰 행크스",
        "팀 알렌",
        "조앤 쿠삭",
        "그레타 리"
      ],
      "genres": [
        "애니메이션",
        "어드벤처",
        "코미디"
      ],
      "nations": [
        "미국"
      ],
      "rating": "전체관람가",
      "runtime": "101",
      "movieNmEn": "Toy Story 5"
    },
    {
      "rnum": "4",
      "rank": "4",
      "rankInten": "-1",
      "rankOldAndNew": "OLD",
      "movieCd": "20252402",
      "movieNm": "군체",
      "openDt": "2026-05-21",
      "salesAmt": "772503260",
      "salesShare": "4.3",
      "salesInten": "-530966510",
      "salesChange": "-40.7",
      "salesAcc": "62268221800",
      "audiCnt": "72022",
      "audiInten": "-56267",
      "audiChange": "-43.9",
      "audiAcc": "5914321",
      "scrnCnt": "624",
      "showCnt": "6881",
      "poster_url": "https://search.pstatic.net/common?type=o&size=304x456&quality=100&direct=true&src=https%3A%2F%2Fs.pstatic.net%2Fmovie.phinf%2F20260521_199%2F1779327167613y2t7q_JPEG%2Fmovie_image.jpg%3Ftype%3Dw640_2",
      "synopsis": "서울 도심의 초고층 빌딩에서 정체불명의 집단 감염사태가 발생한다. 건물은 순식간에 봉쇄되고, 그 안에 있던 사람들은 그대로 고립된다. 처음에는 짐승처럼 기...",
      "naver_rating": "7.88",
      "directors": [
        "연상호"
      ],
      "actors": [
        "전지현",
        "구교환",
        "지창욱",
        "신현빈",
        "김신록"
      ],
      "genres": [
        "액션",
        "스릴러"
      ],
      "nations": [
        "한국"
      ],
      "rating": "15세이상관람가",
      "runtime": "122",
      "movieNmEn": "COLONY"
    },
    {
      "rnum": "5",
      "rank": "5",
      "rankInten": "7",
      "rankOldAndNew": "OLD",
      "movieCd": "20262902",
      "movieNm": "다윗",
      "openDt": "2026-07-10",
      "salesAmt": "601158630",
      "salesShare": "3.3",
      "salesInten": "515122030",
      "salesChange": "598.7",
      "salesAcc": "740618230",
      "audiCnt": "59311",
      "audiInten": "49216",
      "audiChange": "487.5",
      "audiAcc": "75470",
      "scrnCnt": "669",
      "showCnt": "3804",
      "poster_url": "https://search.pstatic.net/common?type=o&size=304x456&quality=100&direct=true&src=https%3A%2F%2Fs.pstatic.net%2Fmovie.phinf%2F20260710_234%2F1783665438821VAl3y_JPEG%2Fmovie_image.jpg%3Ftype%3Dw640_2",
      "synopsis": "평범한 목동 다윗, 두려움을 넘어 역사가 되다! 소년 다윗은 어느 날 선지자 사무엘로부터 왕이 될 운명을 듣게 되지만, 그것이 무엇을 의미하는지 알기도 전에 ...",
      "naver_rating": "9.67",
      "directors": [
        "필 커닝햄",
        "브렌트 도스"
      ],
      "actors": [
        "브랜든 엥그먼",
        "필 위크함",
        "브라이언 스티베일",
        "아담 골드",
        "미리 메시카"
      ],
      "genres": [
        "애니메이션"
      ],
      "nations": [
        "남아프리카공화국",
        "미국"
      ],
      "rating": "전체관람가",
      "runtime": "109",
      "movieNmEn": "David"
    },
    {
      "rnum": "6",
      "rank": "6",
      "rankInten": "-1",
      "rankOldAndNew": "OLD",
      "movieCd": "20263530",
      "movieNm": "마티 슈프림",
      "openDt": "2026-07-01",
      "salesAmt": "345972710",
      "salesShare": "1.9",
      "salesInten": "-374150640",
      "salesChange": "-52.0",
      "salesAcc": "1086353060",
      "audiCnt": "31832",
      "audiInten": "-37234",
      "audiChange": "-53.9",
      "audiAcc": "102095",
      "scrnCnt": "562",
      "showCnt": "3173",
      "poster_url": "https://search.pstatic.net/common?type=o&size=304x456&quality=100&direct=true&src=https%3A%2F%2Fs.pstatic.net%2Fmovie.phinf%2F20260610_239%2F1781068492766CU2dN_JPEG%2Fmovie_image.jpg%3Ftype%3Dw640_2",
      "synopsis": "\"어떤 대가를 치르더라도 반드시 가장 높은 곳으로!\" 탁구로 인생 역전을 꿈꾸는 마티 마우저는 굴욕적인 패배 후 누구도 무시할 수 없는 성공을 손에 넣기로 결심한다. 최고가 ...",
      "naver_rating": "8.16",
      "directors": [
        "조쉬 사프디"
      ],
      "actors": [
        "티모시 샬라메",
        "기네스 팰트로우",
        "오데사 아지온",
        "타일러 더 크리에이터",
        "아벨 페라라"
      ],
      "genres": [
        "드라마"
      ],
      "nations": [
        "미국"
      ],
      "rating": "15세이상관람가",
      "runtime": "149",
      "movieNmEn": "Marty Supreme"
    },
    {
      "rnum": "7",
      "rank": "7",
      "rankInten": "-3",
      "rankOldAndNew": "OLD",
      "movieCd": "20248252",
      "movieNm": "와일드 씽",
      "openDt": "2026-06-03",
      "salesAmt": "263243900",
      "salesShare": "1.5",
      "salesInten": "-401987290",
      "salesChange": "-60.4",
      "salesAcc": "12874211290",
      "audiCnt": "29618",
      "audiInten": "-39957",
      "audiChange": "-57.4",
      "audiAcc": "1333233",
      "scrnCnt": "501",
      "showCnt": "3770",
      "poster_url": "https://search.pstatic.net/common?type=o&size=304x456&quality=100&direct=true&src=https%3A%2F%2Fs.pstatic.net%2Fmovie.phinf%2F20260612_104%2F1781234312440vFV51_JPEG%2Fmovie_image.jpg%3Ftype%3Dw640_2",
      "synopsis": "",
      "naver_rating": "",
      "directors": [
        "손재곤"
      ],
      "actors": [
        "강동원",
        "엄태구",
        "박지현",
        "오정세",
        "안현호"
      ],
      "genres": [
        "코미디"
      ],
      "nations": [
        "한국"
      ],
      "rating": "12세이상관람가",
      "runtime": "107",
      "movieNmEn": "Wild Sing"
    },
    {
      "rnum": "8",
      "rank": "8",
      "rankInten": "-2",
      "rankOldAndNew": "OLD",
      "movieCd": "20264027",
      "movieNm": "극장판 도라에몽: 신 진구의 해저비밀성",
      "openDt": "2026-07-01",
      "salesAmt": "178146050",
      "salesShare": "1.0",
      "salesInten": "-174811250",
      "salesChange": "-49.5",
      "salesAcc": "541922350",
      "audiCnt": "17093",
      "audiInten": "-22062",
      "audiChange": "-56.3",
      "audiAcc": "57150",
      "scrnCnt": "199",
      "showCnt": "2123",
      "poster_url": "https://search.pstatic.net/common?type=o&size=304x456&quality=100&direct=true&src=https%3A%2F%2Fs.pstatic.net%2Fmovie.phinf%2F20260701_60%2F1782880689685LGkLk_JPEG%2Fmovie_image.jpg%3Ftype%3Dw640_2",
      "synopsis": "이번 여름방학은 바닷속 캠핑이다! 숨이 멎을 듯한 놀라움이 가득한 두근두근 해저 대모험! 여름방학 캠핑 장소를 두고 의견이 갈린 진구와 친구들은 도라에몽의 제안으로 바...",
      "naver_rating": "8.79",
      "directors": [
        "야지마 테츠오"
      ],
      "actors": [
        "윤아영",
        "김정아",
        "조현정",
        "이현주",
        "최낙윤"
      ],
      "genres": [
        "애니메이션"
      ],
      "nations": [
        "일본"
      ],
      "rating": "전체관람가",
      "runtime": "101",
      "movieNmEn": "Doraemon the Movie: New Nobita and the Castle of the Undersea Devil"
    },
    {
      "rnum": "9",
      "rank": "9",
      "rankInten": "-2",
      "rankOldAndNew": "OLD",
      "movieCd": "20263030",
      "movieNm": "백룸",
      "openDt": "2026-05-27",
      "salesAmt": "191941600",
      "salesShare": "1.1",
      "salesInten": "-215228290",
      "salesChange": "-52.9",
      "salesAcc": "12911860110",
      "audiCnt": "16980",
      "audiInten": "-21150",
      "audiChange": "-55.5",
      "audiAcc": "1209069",
      "scrnCnt": "229",
      "showCnt": "1371",
      "poster_url": "",
      "synopsis": "\"시작은 호기심이었다\" 그곳은 대체 무엇인가? 낯설지만 익숙한 세계 출구도 입구도 찾을 수 없다. 당신도 입장하시겠습니까?",
      "naver_rating": "7.95",
      "directors": [
        "케인 파슨스"
      ],
      "actors": [
        "치웨텔 에지오포",
        "레나테 레인스베"
      ],
      "genres": [
        "공포(호러)",
        "스릴러"
      ],
      "nations": [
        "미국"
      ],
      "rating": "15세이상관람가",
      "runtime": "110",
      "movieNmEn": "Backrooms"
    },
    {
      "rnum": "10",
      "rank": "10",
      "rankInten": "-2",
      "rankOldAndNew": "OLD",
      "movieCd": "20264056",
      "movieNm": "그린랜드 2: 마이그레이션",
      "openDt": "2026-07-01",
      "salesAmt": "161570120",
      "salesShare": "0.9",
      "salesInten": "-173544810",
      "salesChange": "-51.8",
      "salesAcc": "501383400",
      "audiCnt": "16971",
      "audiInten": "-18184",
      "audiChange": "-51.7",
      "audiAcc": "52544",
      "scrnCnt": "337",
      "showCnt": "1901",
      "poster_url": "",
      "synopsis": "혜성 충돌로 문명이 붕괴된 지 5년 후, 방사능 폭풍을 피해 지하 벙커에서 살아남은 인류는 끝이 보이지 않는 지하 생활을 이어가고 있다. 점점 심해지는 지진과...",
      "naver_rating": "8.21",
      "directors": [
        "릭 로먼 워"
      ],
      "actors": [
        "제라드 버틀러",
        "모레나 바카린",
        "로만 그리핀 데이비스"
      ],
      "genres": [
        "액션",
        "SF"
      ],
      "nations": [
        "영국"
      ],
      "rating": "12세이상관람가",
      "runtime": "97",
      "movieNmEn": "Greenland: Migration"
    }
  ]
}